icemac.recurrence-1.7-py3.7-nspkg.pth
icemac/recurrence/__init__.py
icemac/recurrence/base.py
icemac/recurrence/configure.zcml
icemac/recurrence/conftest.py
icemac/recurrence/daily.py
icemac/recurrence/i18n.py
icemac/recurrence/interfaces.py
icemac/recurrence/monthly.py
icemac/recurrence/recurrence.py
icemac/recurrence/test_base.py
icemac/recurrence/test_daily.py
icemac/recurrence/test_monthly.py
icemac/recurrence/test_recurrence.py
icemac/recurrence/test_weekly.py
icemac/recurrence/test_yearly.py
icemac/recurrence/weekly.py
icemac/recurrence/yearly.py
icemac.recurrence-1.7.dist-info/LICENSE.TXT
icemac.recurrence-1.7.dist-info/METADATA
icemac.recurrence-1.7.dist-info/WHEEL
icemac.recurrence-1.7.dist-info/namespace_packages.txt
icemac.recurrence-1.7.dist-info/top_level.txt
icemac.recurrence-1.7.dist-info/RECORD
