Metadata-Version: 2.1
Name: icemac.recurrence
Version: 1.7
Summary: Compute recurrences of events
Home-page: https://github.com/icemac/icemac.recurrence
Author: Michael Howitz
Author-email: icemac@gmx.net
License: MIT
Download-URL: https://pypi.org/project/icemac.recurrence
Keywords: calendar event recurring recurrence datetime
Platform: UNKNOWN
Classifier: Development Status :: 5 - Production/Stable
Classifier: License :: OSI Approved :: MIT License
Classifier: Natural Language :: English
Classifier: Operating System :: OS Independent
Classifier: Programming Language :: Python :: 2.7
Classifier: Programming Language :: Python :: 3.6
Classifier: Programming Language :: Python :: 3.7
Classifier: Programming Language :: Python :: 3.8
Classifier: Programming Language :: Python :: Implementation :: CPython
Classifier: Programming Language :: Python :: Implementation :: PyPy
Requires-Dist: gocept.month (>=2)
Requires-Dist: grokcore.component (>=2.6)
Requires-Dist: setuptools
Requires-Dist: zope.cachedescriptors
Requires-Dist: zope.component
Requires-Dist: zope.globalrequest
Requires-Dist: zope.i18nmessageid
Requires-Dist: zope.interface
Provides-Extra: test
Requires-Dist: zope.configuration ; extra == 'test'
